{
  "Landing": {
    "title": "Контролюйте свої фінанси.",
    "subtitle": "Плануйте, відстежуйте та керуйте своїм бюджетом легко з",
    "highlight": "My Budget"
  },
  "Home": {
    "title": "My Budget",
    "description": "Контролюйте свої фінанси. Плануйте, відстежуйте та керуйте своїм бюджетом легко з My Budget."
  },
  "Dashboard": {
    "pageTitle": "Аналітика",
    "pageDescription": "Отримайте чисту карту свого бюджету з реальними даними.",
    "noData": "Ще немає записаних {entity}.",
    "pieTotalMessage": "Всього за період",
    "monthlySummaryByCurrency": "Місячна аналітика за валютою"
  },
  "ScheduledPayments": {
    "pageTitle": "Регулярні платежі",
    "pageDescription": "Керуйте своїми регулярними платежами.",
    "createScheduledPayment": "Створити регулярний платіж",
    "nextPayment": "Наступний платіж",
    "noScheduledPayments": "Ще немає регулярних платежів."
  },
  "Groups": {
    "pageTitle": "Групи",
    "pageDescription": "Керуйте своїми групами та їх учасниками.",
    "groupImage": "Зображення групи",
    "createGroup": "Створити групу",
    "updateGroup": "Оновити группу",
    "createdBy": "Автор",
    "members": "Учасники",
    "addMember": "Додати учасника",
    "addDialogDescription": "Додати емейл для запрошення нового учасника",
    "invitedMembers": "Запрошені учасники",
    "pendingMembers": "Учасники в очікуванні"
  },
  "Categories": {
    "pageTitle": "Категорії",
    "pageDescription": "Керуйте своїми категоріями",
    "createCategory": "Створити категорію",
    "categoryType": "Тип категорії"
  },
  "Shoppings": {
    "pageTitle": "Список покупок",
    "pageDescription": "Керуйте своїм списком покупок",
    "addProduct": "Додати товар",
    "itemsSummary": "Усього {count, plural, \n    one {# товар} \n    few {# товари} \n    many {# товарів} \n    other {# товарів}\n  } на суму {amount}"
  },
  "Vehicles": {
    "pageTitle": "Транспортні засоби",
    "pageDescription": "Керуйте своїми транспортними засобами",
    "addVehicle": "Додати засіб",
    "addVehiclePage": "Додати транспортний засіб",
    "addVehiclePageDescription": "Додати транспортний засіб",
    "updateVehiclePageTitle": "Оновити транспортний засіб",
    "updateVehiclePageDesc": "Оновити транспортний засіб",
    "currentOdometer": "Поточні показники одометру",
    "lastOdometer": "Остання заправка",
    "dashboard": "Аналітика",
    "fuel": "Пальне",
    "expenses": "Витрати",
    "service": "Обслуговування",
    "importDialogTitle": "Буде імпортовано наступні записи",
    "record": "{count, plural, one {запис} few {записів} many {записів} other {записів}}",
    "deleteFuelRecordMessage": "Ви впевнені що хочете видалити цей запис про заправку?",
    "fuelRecordDialogTitle": "{isEdit, select, true {Редагувати} false {Додати} other {Додати}} запис про заправку"
  },
  "Sidebar": {
    "home": "Головна",
    "dashboard": "Аналітика",
    "scheduledPayments": "Регулярні платежі",
    "groups": "Групи",
    "categories": "Категорії",
    "shoppingList": "Список покупок",
    "personalWorkspace": "Власний простір",
    "vehiclesList": "Транспортні засоби"
  },
  "Auth": {
    "login": {
      "pageTitle": "Увійти",
      "description": "Увійти в свій аккаунт.",
      "title": "Увійдіть щоб продовжити.",
      "loginBtn": "Увійти",
      "noAccount": "Немає аккаунту?",
      "register": "Реєстрація"
    },
    "register": {
      "pageTitle": "Реєстрація",
      "description": "Зареєструвати аккаунт.",
      "title": "Розпочати з",
      "registerBtn": "Реєстрація"
    }
  },
  "Common": {
    "inputs": {
      "firstName": "Ім'я",
      "firstNamePlaceholder": "Введіть ім'я",
      "lastName": "Прізвище",
      "lastNamePlaceholder": "Введіть прізвище",
      "email": "Поштова адреса",
      "emailPlaceholder": "Введіть поштову адресу",
      "password": "Пароль",
      "passwordPlaceholder": "Введіть пароль",
      "description": "Опис",
      "amount": "Сума",
      "title": "Назва",
      "unit": "Одиниця",
      "quantity": "Кількість",
      "listName": "Назва списку",
      "odometer": "Одометр",
      "vinCode": "VIN Код"
    },
    "selectors": {
      "currencyLabel": "Валюта за замовченням",
      "currencyPlaceholder": "Виберіть валюту",
      "currency": "Валюта",
      "date": "Дата",
      "categoryLabel": "Категорія",
      "categoryPlaceholder": "Виберіть категорію",
      "noCategories": "Немає категорій",
      "createCategory": "Створити категорію",
      "defaultCategoryLabel": "Категорія за замовченням",
      "defaultCategoryPlaceholder": "Виберіть категорію за замовченням",
      "proceedDate": "Дата проведення",
      "scheduledPaymentFrequency": "Частота платежу",
      "vehicleType": "Тип засобу",
      "fuelType": "Вид пального",
      "linkGroup": "Пов'язати з групою",
      "linkGroupDescription": "Члени вибраної групи отримають доступ до цього транспортного засобу",
      "linkVehicleCategoryDesc": "Відображати витрати на транспортний засіб у категорії загальних витрат"
    },
    "switch": {
      "skipNextPayment": "Пропустити наступний платіж",
      "skipNextPaymentDescription": "Якщо увімкнено, найближчий запланований платіж буде пропущено один раз.",
      "createImportedTransaction": "Створити {count, plural, one {транзакцію} few {транзакції} many {транзакції} other {транзакції}}",
      "createImportedTransactionDesc": "Буде створено для загального списку витрат"
    },
    "buttons": {
      "back": "Назад",
      "getStarted": "Розпочати",
      "google": "Увійти з Google",
      "signOut": "Вийти",
      "create": "Створити {entity}",
      "update": "Оновити",
      "add": "Додати",
      "createTransaction": "Додати транзакцію",
      "save": "Зберегти",
      "confirm": "Підтвердити",
      "cancel": "Скасувати",
      "clearFilter": "Очистити",
      "recipeScan": "Сканувати чек",
      "createScheduledPayment": "Створити регулярний платіж"
    },
    "titles": {
      "uploadImage": "Завантажити зображення"
    }
  },
  "UserMenu": {
    "profile": "Мій профіль"
  },
  "UserProfile": {
    "pageTitle": "Мій профіль",
    "description": "Тут ви можете змінити свій профіль та налаштування.",
    "settings": "Налаштування"
  },
  "Notifications": {
    "notAuthorized": "Ви не авторизовані",
    "notFound": "Сторінка не знайдена",
    "forbidden": "Ви не маєте доступу до цієї сторінки",
    "mongoValidationError": "Перевірте правильність введених даних",
    "mongoCastError": "Неправильний формат ID",
    "serverError": "Помилка серверу",
    "error": "Упс! Щось пішло не так",
    "success": "Операція успішно завершена",
    "userCreated": "Користувача `{name}` успішно створено",
    "userFound": "Користувача `{name}` знайдено.",
    "userUpdated": "Користувача успішно оновлено",
    "userNotFound": "Користувача не знайдено",
    "wrongCredentials": "Неправильні дані",
    "created": "{entity} {name} створено",
    "updated": "{entity} {name} оновлено",
    "deleted": "{entity} {name} видалено",
    "imageUploaded": "Зображення завантажено",
    "imageUploadFailed": "Завантаження зображення не вдалося",
    "shoppingList": "Список покупок {name} було {action}",
    "actionCreated": "створено",
    "actionUpdated": "оновлено",
    "actionDeleted": "видалено"
  },
  "Table": {
    "actions": "Дії",
    "noResults": "Немає результатів",
    "pageSize": "Рядків на сторінці",
    "category": "Категорія",
    "description": "Опис",
    "createdBy": "Автор",
    "createdAt": "Створено",
    "group": "Група",
    "updatedAt": "Оновлено",
    "amount": "Сума",
    "shoppingTitle": "Назва",
    "items": "Позиції",
    "status": "Статус",
    "edit": "Редагувати",
    "delete": "Видалити",
    "proceedDate": "Дата проведення",
    "location": "Локація",
    "liters": "Літри",
    "pricePerLiter": "Ціна за літр",
    "odometer": "Одометр",
    "fullTank": "Повний бак",
    "notes": "Нотатки",
    "transaction": "Транзакція",
    "currentOdometer": "Поточний одометр",
    "trip": "Поїздка"
  },
  "Status": {
    "completed": "Завершено",
    "inProgress": "В процесі",
    "archived": "Архів",
    "paused": "Призупинено",
    "cancelled": "Скасовано",
    "active": "Активний"
  },
  "CategoryTypes": {
    "outgoing": "Витрати",
    "incoming": "Надходження"
  },
  "Dialogs": {
    "confirmation": "Підтвердження",
    "confirmationMessage": "Ви впевнені, що хочете видалити цю {entity}?",
    "description": "Внесіть зміни у транзакцію",
    "createTitle": "Створити {entity}",
    "editTitle": "Редагувати {entity}",
    "deleteGroupMemberMessage": "Ви впевнені, що хочете видалити цього учасника групи?",
    "deleteShoppingItemMessage": "Ви впевнені, що хочете видалити цей список покупок?",
    "selectColor": "Оберіть колір",
    "updateUnitDialogDescription": "Внесіть зміни",
    "deleteScheduledPaymentMessage": "Ви впевнені, що хочете видалити цю оплату?",
    "deleteVehicleMessage": "Ви впевнені що хочете видалити цей транспортний засіб?"
  },
  "Entities": {
    "transaction": {
      "nominative": "Транзакція",
      "genitive": "транзакції",
      "accusative": "транзакцію",
      "plural": "транзакції"
    },
    "group": {
      "nominative": "Група",
      "genitive": "груп",
      "accusative": "групу",
      "plural": "груп"
    },
    "category": {
      "nominative": "Категорія",
      "genitive": "категорії",
      "accusative": "категорію",
      "plural": "категорії"
    },
    "shopping": {
      "nominative": "Список покупок",
      "genitive": "списків покупок",
      "accusative": "список покупок",
      "plural": "списки покупок"
    },
    "unit": {
      "nominative": "Одиниця",
      "genitive": "одиниць",
      "accusative": "одиницю",
      "plural": "одиниць"
    },
    "quantity": {
      "nominative": "Кількість"
    },
    "expense": {
      "nominative": "Витрати",
      "genitive": "витрат",
      "accusative": "витрати",
      "plural": "витрат"
    },
    "income": {
      "nominative": "Надходження",
      "genitive": "надходжень",
      "accusative": "надходження",
      "plural": "надходжень"
    },
    "scheduledPayment": {
      "nominative": "Регулярний платіж",
      "genitive": "регулярних платежів",
      "accusative": "регулярний платіж",
      "plural": "регулярні платежі"
    }
  },
  "Units": {
    "groups": {
      "count": "Кількість",
      "weight": "Вага",
      "volume": "Обʼєм"
    },

    "display": {
      "pcs": "Штуки",
      "pack": "Пачки",
      "box": "Коробки",
      "bag": "Пакети",
      "bottle": "Пляшки",
      "can": "Банки",
      "g": "Грамми",
      "kg": "Кілограми",
      "oz": "Унці",
      "lb": "Фунти",
      "ml": "Мілілітри",
      "l": "Літри"
    },

    "pcs": "{count, plural, one {штука} few {штуки} many {штук} other {штук}}",
    "pack": "{count, plural, one {пачка} few {пачки} many {пачок} other {пачок}}",
    "box": "{count, plural, one {коробка} few {коробки} many {коробок} other {коробок}}",
    "bag": "{count, plural, one {пакет} few {пакети} many {пакетів} other {пакетів}}",
    "bottle": "{count, plural, one {пляшка} few {пляшки} many {пляшок} other {пляшок}}",
    "can": "{count, plural, one {банка} few {банки} many {банок} other {банок}}",

    "oz": "{count, plural, one {унція} few {унції} many {унцій} other {унцій}}",
    "lb": "{count, plural, one {фунт} few {фунти} many {фунтів} other {фунтів}}",

    "g": "{count, plural, one {грам} few {грами} many {грамів} other {грамів}}",
    "kg": "{count, plural, one {кілограм} few {кілограми} many {кілограмів} other {кілограмів}}",
    "ml": "{count, plural, one {мілілітр} few {мілілітри} many {мілілітрів} other {мілілітрів}}",
    "l": "{count, plural, one {літр} few {літри} many {літрів} other {літрів}}"
  },
  "monthMap": {
    "1": "Січень",
    "2": "Лютий",
    "3": "Березень",
    "4": "Квітень",
    "5": "Травень",
    "6": "Червень",
    "7": "Липень",
    "8": "Серпень",
    "9": "Вересень",
    "10": "Жовтень",
    "11": "Листопад",
    "12": "Грудень"
  },
  "FormValidations": {
    "baseRequired": "Значення є обов'язковим.",
    "categoryRequired": "Будь ласка, оберіть категорію.",
    "currencyRequired": "Валюта є обов'язковою.",
    "invalidEmail": "Невірний формат електронної пошти.",
    "shoppingItemsRequired": "Додайте хочаб один елемент в список."
  },
  "Frequency": {
    "daily": "Щодня",
    "weekly": "Щотижня",
    "2weeks": "Кожних два тижні",
    "4weeks": "Кожних чотири тижні",
    "monthly": "Щомісяця",
    "annually": "Щорічно"
  },

  "FuelTypes": {
    "title": "Тип пального",
    "petrol": "Бензин",
    "diesel": "Дизель",
    "gas": "Газ",
    "electric": "Електро",
    "hybrid": "Гібрид"
  },

  "VehicleTypes": {
    "title": "Тип транспортного засобу",
    "car": "Авто",
    "bicycle": "Велосипед"
  }
}
